haaaash/__init__.py
haaaash/__main__.py
haaaash/about.py
haaaash/console.py
haaaash/enumerate.py
haaaash/file_mod.py
haaaash/hash_func.py
haaaash/hashs.py
haaaash/outs.py
haaaash/shell.py
haaaash/gui/__init__.py
haaaash/gui/main.py
haaaash_expansion-0.8.5.dist-info/LICENSE
haaaash_expansion-0.8.5.dist-info/METADATA
haaaash_expansion-0.8.5.dist-info/WHEEL
haaaash_expansion-0.8.5.dist-info/entry_points.txt
haaaash_expansion-0.8.5.dist-info/top_level.txt
haaaash_expansion-0.8.5.dist-info/RECORD
