Metadata-Version: 2.1
Name: haaaash-expansion
Version: 0.8.5
Summary: hash 批量计算器 高级版
Author: Gudupao
Author-email: official@gudupao.top
Classifier: Development Status :: 3 - Alpha
Classifier: Intended Audience :: Developers
Classifier: License :: OSI Approved :: MIT License
Classifier: Programming Language :: Python :: 3.9
Classifier: Programming Language :: Python :: 3.10
Classifier: Programming Language :: Python :: 3.11
Classifier: Programming Language :: Python :: 3.12
Classifier: Programming Language :: Python :: 3.13
License-File: LICENSE
Requires-Dist: PySide6>=6.5.0
